improved_user/__init__.py
improved_user/admin.py
improved_user/apps.py
improved_user/factories.py
improved_user/forms.py
improved_user/managers.py
improved_user/model_mixins.py
improved_user/models.py
improved_user/migrations/0001_initial.py
improved_user/migrations/__init__.py
django_improved_user-2.1.0.dist-info/LICENSE
django_improved_user-2.1.0.dist-info/WHEEL
django_improved_user-2.1.0.dist-info/METADATA
django_improved_user-2.1.0.dist-info/RECORD
