Metadata-Version: 2.1
Name: django-improved-user
Version: 2.1.0
Summary: Compose new Django User models that follow best-practices for international names and authenticate via email instead of username.
Author: Russell Keith-Magee, Andrew Pinkham
Requires-Python: >=3.6
Classifier: Development Status :: 5 - Production/Stable
Classifier: Intended Audience :: Developers
Classifier: License :: OSI Approved :: BSD License
Classifier: Operating System :: OS Independent
Classifier: Topic :: Software Development :: Libraries
Classifier: Programming Language :: Python :: 3
Classifier: Programming Language :: Python :: 3.6
Classifier: Programming Language :: Python :: 3.7
Classifier: Programming Language :: Python :: 3.8
Classifier: Programming Language :: Python :: 3.9
Classifier: Programming Language :: Python :: 3.10
Classifier: Programming Language :: Python :: 3.11
Classifier: Programming Language :: Python :: 3.12
Classifier: Programming Language :: Python :: 3 :: Only
Classifier: Framework :: Django
Classifier: Framework :: Django :: 2.2
Classifier: Framework :: Django :: 3.0
Classifier: Framework :: Django :: 3.1
Classifier: Framework :: Django :: 3.2
Classifier: Framework :: Django :: 4.0
Classifier: Framework :: Django :: 4.1
Classifier: Framework :: Django :: 4.2
Requires-Dist: django>=2.2
Requires-Dist: factory-boy>=2.9 ; extra == "factory"
Requires-Dist: Faker>=0.8 ; extra == "factory"
Requires-Dist: python-dateutil>=2.6 ; extra == "factory"
Project-URL: Documentation, https://django-improved-user.rtfd.io
Project-URL: Source, https://github.com/jambonrose/django-improved-user/
Project-URL: Tracker, https://github.com/jambonrose/django-improved-user/issues
Provides-Extra: factory
